<?xml version="1.0" encoding="utf-8"?>
<!DOCTYPE hibernate-mapping PUBLIC "-//Hibernate/Hibernate Mapping DTD 3.0//EN"
"http://www.hibernate.org/dtd/hibernate-mapping-3.0.dtd">
<!-- 
    Mapping file autogenerated by MyEclipse Persistence Tools
-->
<hibernate-mapping>
    <class name="com.jobchat.entity.JCompanyuser" table="j_companyuser" catalog="jobchat">
        <id name="companyuserId" type="integer">
            <column name="companyuser_id" />
            <generator class="native" />
        </id>
        <many-to-one name="JCompany" class="com.jobchat.entity.JCompany" fetch="select"  lazy="false">
            <column name="company_id" not-null="true" />
        </many-to-one>
        <property name="username" type="string">
            <column name="username">
                <comment>联系人名称</comment>
            </column>
        </property>
        <property name="userphone" type="string">
            <column name="userphone">
                <comment>电话</comment>
            </column>
        </property>
        <property name="userphone2" type="string">
            <column name="userphone2">
                <comment>手机</comment>
            </column>
        </property>
        <property name="userqq" type="string">
            <column name="userqq">
                <comment>qq</comment>
            </column>
        </property>
        <property name="useraddress" type="string">
            <column name="useraddress">
                <comment>办公地址</comment>
            </column>
        </property>
        <property name="userphone3" type="string">
            <column name="userphone3">
                <comment>总机</comment>
            </column>
        </property>
        <property name="userphone4" type="string">
            <column name="userphone4">
                <comment>人事部门电话</comment>
            </column>
        </property>
        <property name="userphone5" type="string">
            <column name="userphone5">
                <comment>业务部门电话</comment>
            </column>
        </property>
        <property name="userphone6" type="string">
            <column name="userphone6">
                <comment>客服电话</comment>
            </column>
        </property>
        <property name="url" type="string">
            <column name="url">
                <comment>网站</comment>
            </column>
        </property>
        <property name="weichat" type="string">
            <column name="weichat">
                <comment>微信公众号</comment>
            </column>
        </property>
        <property name="ptime" type="string">
            <column name="ptime" />
        </property>
        <property name="status" type="short">
            <column name="status" />
        </property>
    </class>
</hibernate-mapping>
