<?xml version="1.0" encoding="utf-8"?>
<!DOCTYPE hibernate-mapping PUBLIC "-//Hibernate/Hibernate Mapping DTD 3.0//EN"
"http://www.hibernate.org/dtd/hibernate-mapping-3.0.dtd">
<!-- 
    Mapping file autogenerated by MyEclipse Persistence Tools
-->
<hibernate-mapping>
    <class name="com.jobchat.entity.JMessages" table="j_messages" catalog="jobchat">
        <id name="messagesId" type="integer">
            <column name="messages_id" />
            <generator class="native" />
        </id>
        <many-to-one name="JUser" class="com.jobchat.entity.JUser" fetch="select"  lazy="false">
            <column name="user_id" not-null="true" />
        </many-to-one>
        <property name="messagesType" type="string">
            <column name="messages_type" length="200" />
        </property>
        <property name="messagesInfo" type="string">
            <column name="messages_info" length="300" not-null="true" />
        </property>
        <property name="messagesTime" type="string">
            <column name="messages_time" length="200" not-null="true" />
        </property>
        <property name="messagesCollectnum" type="integer">
            <column name="messages_collectnum" not-null="true" />
        </property>
        <property name="messagesCommentnum" type="integer">
            <column name="messages_commentnum" not-null="true" />
        </property>
        <property name="messagesTranspondnum" type="integer">
            <column name="messages_transpondnum" not-null="true" />
        </property>
        <property name="messagesAgreenum" type="integer">
            <column name="messages_agreenum" not-null="true" />
        </property>
        <property name="messagesReadnum" type="integer">
            <column name="messages_readnum" not-null="true" />
        </property>
        <property name="messagesPicture" type="string">
            <column name="messages_picture" length="800" />
        </property>
        <property name="messagesDevice" type="string">
            <column name="messages_device" length="20" />
        </property>
        <property name="messagesStatus" type="integer">
            <column name="messages_status" />
        </property>
        <set name="JCollectionses" inverse="true">
            <key>
                <column name="messages_id" not-null="true" />
            </key>
            <one-to-many class="com.jobchat.entity.JCollections" />
        </set>
        <set name="JCommentses" inverse="true">
            <key>
                <column name="message_id" not-null="true" />
            </key>
            <one-to-many class="com.jobchat.entity.JComments" />
        </set>
    </class>
</hibernate-mapping>
